<?xml version="1.0" encoding="windows-1251"?>

<string_table>
	<!-- mcm tab/group -->
	<string id ="ui_mcm_menu_seals_custom_layers_scope">
		<text>Scope</text>
	</string>	
	<!-- seal mcm toggle -->
	<string id ="ui_mcm_seals_3dss_show">
		<text>3DSS</text>
	</string>
	<string id ="ui_mcm_seals_3dss_show_desc">
		<text>This seal signifies that the weapon has built-in 3DSS support</text>
	</string>	
	<!-- seal caption -->
	<string id ="ui_seals_3dss_caption">
		<text>3D Scopes</text>
	</string>			
</string_table>  